agin/__init__.py
agin/agin.py
aigic_test-1.0.4.dist-info/METADATA
aigic_test-1.0.4.dist-info/WHEEL
aigic_test-1.0.4.dist-info/top_level.txt
aigic_test-1.0.4.dist-info/RECORD
